facedb/__init__.py
facedb/db.py
facedb/db_models.py
facedb/db_tools.py
facedb/query.py
FaceDB-0.0.10.dist-info/LICENSE
FaceDB-0.0.10.dist-info/METADATA
FaceDB-0.0.10.dist-info/WHEEL
FaceDB-0.0.10.dist-info/top_level.txt
FaceDB-0.0.10.dist-info/RECORD
