Metadata-Version: 2.1
Name: FaceDB
Version: 0.0.10
Summary: A python package for large scale face recognition.
Home-page: https://github.com/shhossain/facedb
Author: sifat (shhossain)
Project-URL: Documentation, https://github.com/shhossain/facedb
Project-URL: Source, https://github.com/shhossain/facedb
Project-URL: Bug Tracker, https://github.com/shhossain/facedb/issues
Keywords: python,face,recognition
Classifier: Development Status :: 3 - Alpha
Classifier: Intended Audience :: Developers
Classifier: Intended Audience :: Education
Classifier: Intended Audience :: Science/Research
Classifier: License :: OSI Approved :: MIT License
Classifier: Programming Language :: Python :: 3
Classifier: Programming Language :: Python :: 3.6
Classifier: Programming Language :: Python :: 3.7
Classifier: Programming Language :: Python :: 3.8
Classifier: Programming Language :: Python :: 3.9
Classifier: Programming Language :: Python :: 3.10
Classifier: Topic :: Scientific/Engineering :: Artificial Intelligence
Classifier: Topic :: Software Development :: Libraries :: Python Modules
Classifier: Topic :: Text Processing :: Linguistic
Classifier: Topic :: Utilities
Classifier: Operating System :: OS Independent
Requires-Python: >=3.7
License-File: LICENSE
Requires-Dist: chromadb
Requires-Dist: pillow
Requires-Dist: opencv-python
Requires-Dist: face-recognition
